{
  "language": "Tagalog",
  "lastRetrievedLetterIndex": 14,
  "lastRowId": 65922,
  "a": {
    "lastPageNum": 88,
    "stoppedAt": 88
  },
  "b": {
    "lastPageNum": 149,
    "stoppedAt": 149
  },
  "c": {
    "lastPageNum": 1,
    "stoppedAt": 1
  },
  "d": {
    "lastPageNum": 94,
    "stoppedAt": 94
  },
  "e": {
    "lastPageNum": 30,
    "stoppedAt": 30
  },
  "g": {
    "lastPageNum": 50,
    "stoppedAt": 50
  },
  "h": {
    "lastPageNum": 78,
    "stoppedAt": 78
  },
  "i": {
    "lastPageNum": 117,
    "stoppedAt": 117
  },
  "j": {
    "lastPageNum": 1,
    "stoppedAt": 1
  },
  "k": {
    "lastPageNum": 225,
    "stoppedAt": 225
  },
  "l": {
    "lastPageNum": 101,
    "stoppedAt": 101
  },
  "m": {
    "lastPageNum": 444,
    "stoppedAt": 444
  },
  "n": {
    "lastPageNum": 62,
    "stoppedAt": 62
  },
  "o": {
    "lastPageNum": 12,
    "stoppedAt": 12
  },
  "p": {
    "lastPageNum": 463,
    "stoppedAt": 435
  }
}